windsuite_sdk/__init__.py
windsuite_sdk/_models_internal.py
windsuite_sdk/fan_control.py
windsuite_sdk/models.py
windsuite_sdk/py.typed
windsuite_sdk/windsuite_sdk.py
windsuite_sdk-0.4.1.dist-info/METADATA
windsuite_sdk-0.4.1.dist-info/WHEEL
windsuite_sdk-0.4.1.dist-info/RECORD
