Metadata-Version: 2.4
Name: windsuite-sdk
Version: 0.4.1
Summary: Windsuite User SDK for the Windshape Software Suite.
Author-email: Jonas Stirnemann <jonas.stirnemann@windshape.com>
Requires-Python: >=3.11
Requires-Dist: loguru>=0.7.3
Requires-Dist: numpy>=2.3.2
Requires-Dist: python-socketio[asyncio-client]>=5.13.0
Requires-Dist: requests>=2.32.4
Requires-Dist: twine>=6.2.0
